[
  {
    "TY": "GEN",
    "A2": "Secondary Author",
    "A3": "Tertiary Author",
    "A4": "Subsidiary Author",
    "AB": "Abstract",
    "AD": "Author Address",
    "AN": "Accession Number",
    "AU": "Author",
    "C1": "Custom 1",
    "C2": "Custom 2",
    "C3": "Custom 3",
    "C4": "Custom 4",
    "C5": "Custom 5",
    "C6": "Custom 6",
    "C7": "Custom 7",
    "C8": "Custom 8",
    "CA": "Caption",
    "CN": "Call Number",
    "CY": "Place Published",
    "DA": "Date",
    "DB": "Name of Database",
    "DO": "DOI",
    "DP": "Database Provider",
    "ET": "Edition",
    "J2": "Alternate Title",
    "KW": "Keywords",
    "L1": "File Attachments",
    "L4": "Figure",
    "LA": "Language",
    "LB": "Label",
    "M1": "Number",
    "M3": "Type of Work",
    "N1": "Notes",
    "NV": "Number of Volumes",
    "OP": "Original Publication",
    "PB": "Publisher",
    "PY": "Year",
    "RI": "Reviewed Item",
    "RN": "Research Notes",
    "RP": "Reprint Edition",
    "SE": "Section",
    "SN": "ISBN/ISSN",
    "SP": "Pages",
    "ST": "Short Title",
    "T2": "Secondary Title",
    "T3": "Tertiary Title",
    "TA": "Translated Author",
    "TI": "Title",
    "TT": "Translated Title",
    "UR": "URL",
    "VL": "Volume",
    "Y2": "Access Date"
  },
  {
    "TY": "ABST",
    "AB": "Abstract",
    "AD": "Author Address",
    "AN": "Accession Number",
    "AU": "Author",
    "C1": "Legal Note",
    "C2": "PMCID",
    "C6": "NIHMSID",
    "C7": "Article Number",
    "CA": "Caption",
    "CN": "Call Number",
    "DA": "Date",
    "DB": "Name of Database",
    "DO": "DOI",
    "DP": "Database Provider",
    "ET": "Epub Date",
    "J2": "Alternate Journal",
    "KW": "Keywords",
    "L1": "File Attachments",
    "L4": "Figure",
    "LA": "Language",
    "LB": "Label",
    "IS": "Issue",
    "M2": "Start Page",
    "M3": "Type of Article",
    "N1": "Notes",
    "OP": "Original Publication",
    "PY": "Year",
    "RI": "Reviewed Item",
    "RN": "Research Notes",
    "RP": "Reprint Edition",
    "SN": "ISSN",
    "SP": "Pages",
    "ST": "Short Title",
    "T2": "Journal",
    "TA": "Translated Author",
    "TI": "Title",
    "TT": "Translated Title",
    "UR": "URL",
    "VL": "Volume",
    "Y2": "Access Date"
  },
  {
    "TY": "INPR",
    "AB": "Abstract",
    "AD": "Author Address",
    "AN": "Accession Number",
    "AU": "Author",
    "C1": "Legal Note",
    "C2": "PMCID",
    "C6": "NIHMSID",
    "C7": "Article Number",
    "CA": "Caption",
    "CN": "Call Number",
    "DA": "Date",
    "DB": "Name of Database",
    "DO": "DOI",
    "DP": "Database Provider",
    "ET": "Epub Date",
    "J2": "Alternate Journal",
    "KW": "Keywords",
    "L1": "File Attachments",
    "L4": "Figure",
    "LA": "Language",
    "LB": "Label",
    "IS": "Issue",
    "M2": "Start Page",
    "M3": "Type of Article",
    "N1": "Notes",
    "OP": "Original Publication",
    "PY": "Year",
    "RI": "Reviewed Item",
    "RN": "Research Notes",
    "RP": "Reprint Edition",
    "SN": "ISSN",
    "SP": "Pages",
    "ST": "Short Title",
    "T2": "Journal",
    "TA": "Translated Author",
    "TI": "Title",
    "TT": "Translated Title",
    "UR": "URL",
    "VL": "Volume",
    "Y2": "Access Date"
  },
  {
    "TY": "JFULL",
    "AB": "Abstract",
    "AD": "Author Address",
    "AN": "Accession Number",
    "AU": "Author",
    "C1": "Legal Note",
    "C2": "PMCID",
    "C6": "NIHMSID",
    "C7": "Article Number",
    "CA": "Caption",
    "CN": "Call Number",
    "DA": "Date",
    "DB": "Name of Database",
    "DO": "DOI",
    "DP": "Database Provider",
    "ET": "Epub Date",
    "J2": "Alternate Journal",
    "KW": "Keywords",
    "L1": "File Attachments",
    "L4": "Figure",
    "LA": "Language",
    "LB": "Label",
    "IS": "Issue",
    "M2": "Start Page",
    "M3": "Type of Article",
    "N1": "Notes",
    "OP": "Original Publication",
    "PY": "Year",
    "RI": "Reviewed Item",
    "RN": "Research Notes",
    "RP": "Reprint Edition",
    "SN": "ISSN",
    "SP": "Pages",
    "ST": "Short Title",
    "T2": "Journal",
    "TA": "Translated Author",
    "TI": "Title",
    "TT": "Translated Title",
    "UR": "URL",
    "VL": "Volume",
    "Y2": "Access Date"
  },
  {
    "TY": "JOUR",
    "AB": "Abstract",
    "AD": "Author Address",
    "AN": "Accession Number",
    "AU": "Author",
    "C1": "Legal Note",
    "C2": "PMCID",
    "C6": "NIHMSID",
    "C7": "Article Number",
    "CA": "Caption",
    "CN": "Call Number",
    "DA": "Date",
    "DB": "Name of Database",
    "DO": "DOI",
    "DP": "Database Provider",
    "ET": "Epub Date",
    "J2": "Alternate Journal",
    "KW": "Keywords",
    "L1": "File Attachments",
    "L4": "Figure",
    "LA": "Language",
    "LB": "Label",
    "IS": "Issue",
    "M2": "Start Page",
    "M3": "Type of Article",
    "N1": "Notes",
    "OP": "Original Publication",
    "PY": "Year",
    "RI": "Reviewed Item",
    "RN": "Research Notes",
    "RP": "Reprint Edition",
    "SN": "ISSN",
    "SP": "Pages",
    "ST": "Short Title",
    "T2": "Journal",
    "TA": "Translated Author",
    "TI": "Title",
    "TT": "Translated Title",
    "UR": "URL",
    "VL": "Volume",
    "Y2": "Access Date"
  },
  {
    "TY": "AGGR",
    "AB": "Abstract",
    "AD": "Author Address",
    "AN": "Accession Number",
    "AU": "Author",
    "CA": "Caption",
    "CY": "City",
    "DA": "Date Accessed",
    "DB": "Name of Database",
    "DO": "DOI",
    "DP": "Database Provider",
    "ET": "Date Published",
    "J2": "Alternate Title",
    "KW": "Keywords",
    "L1": "File Attachments",
    "L4": "Figure",
    "LA": "Language",
    "LB": "Label",
    "M1": "Publication Number",
    "M3": "Type of Work",
    "N1": "Notes",
    "OP": "Original Publication",
    "PB": "Publisher",
    "PY": "Year",
    "RN": "Research Notes",
    "SE": "Screens",
    "SN": "ISSN/ISBN",
    "SP": "Pages",
    "ST": "Short Title",
    "T2": "Periodical",
    "TA": "Translated Author",
    "TI": "Title",
    "TT": "Translated Title",
    "UR": "URL",
    "VL": "Volume"
  },
  {
    "TY": "ANCIENT",
    "A2": "Editor",
    "A4": "Translator",
    "AB": "Abstract",
    "AD": "Author Address",
    "AN": "Accession Number",
    "AU": "Author",
    "CN": "Call Number",
    "CA": "Caption",
    "CY": "City",
    "DA": "Date",
    "DB": "Name of Database",
    "DO": "DOI",
    "DP": "Database Provider",
    "ET": "Edition",
    "J2": "Abbreviated Publication",
    "KW": "Keywords",
    "L1": "File Attachments",
    "L4": "Figure",
    "LA": "Language",
    "LB": "Label",
    "M1": "Text Number",
    "M3": "Type of Work",
    "N1": "Notes",
    "NV": "Number of Volumes",
    "OP": "Original Publication",
    "PB": "Publisher",
    "PY": "Year",
    "RI": "Reviewed Item",
    "RN": "Research Notes",
    "RP": "Reprint Edition",
    "SN": "ISBN",
    "SP": "Pages",
    "ST": "Short Title",
    "T2": "Publication Title",
    "T3": "Volume Title",
    "TA": "Translated Author",
    "TI": "Title",
    "TT": "Translated Title",
    "UR": "URL",
    "VL": "Volume",
    "Y2": "Access Date"
  },
  {
    "TY": "ART",
    "AB": "Abstract",
    "AD": "Author Address",
    "AN": "Accession Number",
    "AU": "Artist",
    "C3": "Size/Length",
    "CA": "Caption",
    "CN": "Call Number",
    "CY": "City",
    "DA": "Date",
    "DB": "Name of Database",
    "DP": "Database Provider",
    "DO": "DOI",
    "ET": "Edition",
    "J2": "Alternate Title",
    "KW": "Keywords",
    "L1": "File Attachments",
    "L4": "Figure",
    "LA": "Language",
    "LB": "Label",
    "M1": "Size",
    "M3": "Type of Work",
    "N1": "Notes",
    "PB": "Publisher",
    "PY": "Year",
    "RN": "Research Notes",
    "SP": "Description",
    "ST": "Short Title",
    "TI": "Title",
    "TT": "Translated Title",
    "TA": "Translated Author",
    "UR": "URL",
    "Y2": "Access Date"
  },
  {
    "TY": "ADVS",
    "A2": "Performers",
    "A3": "Series Editor",
    "AB": "Abstract",
    "AD": "Author Address",
    "AN": "Accession Number",
    "AU": "Author",
    "C1": "Cast",
    "C2": "Credits",
    "C3": "Size/Length",
    "C5": "Format",
    "CA": "Caption",
    "CN": "Call Number",
    "CY": "City",
    "DA": "Date",
    "DB": "Name of Database",
    "DO": "DOI",
    "DP": "Database Provider",
    "ET": "Edition",
    "J2": "Alternate Title",
    "KW": "Keywords",
    "L1": "File Attachments",
    "L4": "Figure",
    "LA": "Language",
    "LB": "Label",
    "M1": "Number",
    "M3": "Type",
    "N1": "Notes",
    "NV": "Extent of Work",
    "OP": "Contents",
    "PB": "Publisher",
    "PY": "Year",
    "RN": "Research Notes",
    "SN": "ISBN",
    "ST": "Short Title",
    "T3": "Series Title",
    "TA": "Translated Author",
    "TI": "Title",
    "TT": "Translated Title",
    "UR": "URL",
    "VL": "Volume",
    "Y2": "Access Date"
  },
  {
    "TY": "SLIDE",
    "A2": "Performers",
    "A3": "Series Editor",
    "AB": "Abstract",
    "AD": "Author Address",
    "AN": "Accession Number",
    "AU": "Author",
    "C1": "Cast",
    "C2": "Credits",
    "C3": "Size/Length",
    "C5": "Format",
    "CA": "Caption",
    "CN": "Call Number",
    "CY": "City",
    "DA": "Date",
    "DB": "Name of Database",
    "DO": "DOI",
    "DP": "Database Provider",
    "ET": "Edition",
    "J2": "Alternate Title",
    "KW": "Keywords",
    "L1": "File Attachments",
    "L4": "Figure",
    "LA": "Language",
    "LB": "Label",
    "M1": "Number",
    "M3": "Type",
    "N1": "Notes",
    "NV": "Extent of Work",
    "OP": "Contents",
    "PB": "Publisher",
    "PY": "Year",
    "RN": "Research Notes",
    "SN": "ISBN",
    "ST": "Short Title",
    "T3": "Series Title",
    "TA": "Translated Author",
    "TI": "Title",
    "TT": "Translated Title",
    "UR": "URL",
    "VL": "Volume",
    "Y2": "Access Date"
  },
  {
    "TY": "SOUND",
    "A2": "Performers",
    "A3": "Series Editor",
    "AB": "Abstract",
    "AD": "Author Address",
    "AN": "Accession Number",
    "AU": "Author",
    "C1": "Cast",
    "C2": "Credits",
    "C3": "Size/Length",
    "C5": "Format",
    "CA": "Caption",
    "CN": "Call Number",
    "CY": "City",
    "DA": "Date",
    "DB": "Name of Database",
    "DO": "DOI",
    "DP": "Database Provider",
    "ET": "Edition",
    "J2": "Alternate Title",
    "KW": "Keywords",
    "L1": "File Attachments",
    "L4": "Figure",
    "LA": "Language",
    "LB": "Label",
    "M1": "Number",
    "M3": "Type",
    "N1": "Notes",
    "NV": "Extent of Work",
    "OP": "Contents",
    "PB": "Publisher",
    "PY": "Year",
    "RN": "Research Notes",
    "SN": "ISBN",
    "ST": "Short Title",
    "T3": "Series Title",
    "TA": "Translated Author",
    "TI": "Title",
    "TT": "Translated Title",
    "UR": "URL",
    "VL": "Volume",
    "Y2": "Access Date"
  },
  {
    "TY": "VIDEO",
    "A2": "Performers",
    "A3": "Series Editor",
    "AB": "Abstract",
    "AD": "Author Address",
    "AN": "Accession Number",
    "AU": "Author",
    "C1": "Cast",
    "C2": "Credits",
    "C3": "Size/Length",
    "C5": "Format",
    "CA": "Caption",
    "CN": "Call Number",
    "CY": "City",
    "DA": "Date",
    "DB": "Name of Database",
    "DO": "DOI",
    "DP": "Database Provider",
    "ET": "Edition",
    "J2": "Alternate Title",
    "KW": "Keywords",
    "L1": "File Attachments",
    "L4": "Figure",
    "LA": "Language",
    "LB": "Label",
    "M1": "Number",
    "M3": "Type",
    "N1": "Notes",
    "NV": "Extent of Work",
    "OP": "Contents",
    "PB": "Publisher",
    "PY": "Year",
    "RN": "Research Notes",
    "SN": "ISBN",
    "ST": "Short Title",
    "T3": "Series Title",
    "TA": "Translated Author",
    "TI": "Title",
    "TT": "Translated Title",
    "UR": "URL",
    "VL": "Volume",
    "Y2": "Access Date"
  },
  {
    "TY": "BILL",
    "A2": "Sponsor",
    "AB": "Abstract",
    "AD": "Author Address",
    "AN": "Accession Number",
    "CA": "Caption",
    "CN": "Call Number",
    "DA": "Date",
    "DB": "Name of Database",
    "DO": "DOI",
    "DP": "Database Provider",
    "ET": "Session",
    "KW": "Keywords",
    "L1": "File Attachments",
    "L4": "Figure",
    "LA": "Language",
    "LB": "Label",
    "N1": "Notes",
    "M1": "Bill Number",
    "OP": "History",
    "PY": "Year",
    "RN": "Research Notes",
    "SE": "Code Section",
    "SP": "Code Pages",
    "ST": "Short Title",
    "T2": "Code",
    "T3": "Legislative Body",
    "TA": "Translated Author",
    "TI": "Title",
    "TT": "Translated Title",
    "UR": "URL",
    "VL": "Code Volume",
    "Y2": "Access Date"
  },
  {
    "TY": "UNBILL",
    "A2": "Sponsor",
    "AB": "Abstract",
    "AD": "Author Address",
    "AN": "Accession Number",
    "CA": "Caption",
    "CN": "Call Number",
    "DA": "Date",
    "DB": "Name of Database",
    "DO": "DOI",
    "DP": "Database Provider",
    "ET": "Session",
    "KW": "Keywords",
    "L1": "File Attachments",
    "L4": "Figure",
    "LA": "Language",
    "LB": "Label",
    "N1": "Notes",
    "M1": "Bill Number",
    "OP": "History",
    "PY": "Year",
    "RN": "Research Notes",
    "SE": "Code Section",
    "SP": "Code Pages",
    "ST": "Short Title",
    "T2": "Code",
    "T3": "Legislative Body",
    "TA": "Translated Author",
    "TI": "Title",
    "TT": "Translated Title",
    "UR": "URL",
    "VL": "Code Volume",
    "Y2": "Access Date"
  },
  {
    "TY": "BLOG",
    "A2": "Editor",
    "A3": "Illustrator",
    "AB": "Abstract",
    "AD": "Author Address",
    "AN": "Accession Number",
    "AU": "Author",
    "C1": "Author Affiliation",
    "CA": "Caption",
    "CN": "Call Number",
    "CY": "City",
    "DA": "Last Update Date",
    "DB": "Name of Database",
    "DO": "DOI",
    "DP": "Database Provider",
    "ET": "Edition",
    "J2": "Alternate Title",
    "KW": "Keywords",
    "L1": "File Attachments",
    "L4": "Figure",
    "LA": "Language",
    "LB": "Label",
    "M3": "Type of Medium",
    "N1": "Notes",
    "OP": "Content",
    "PB": "Publisher",
    "PY": "Year",
    "RN": "Research Notes",
    "SE": "Message Number",
    "SN": "ISBN",
    "SP": "Description",
    "ST": "Short Title",
    "T2": "Title of WebLog",
    "T3": "Institution",
    "TA": "Translated Author",
    "TI": "Title of Entry",
    "TT": "Translated Title",
    "UR": "URL",
    "VL": "Access Year",
    "Y2": "Access Date"
  },
  {
    "TY": "BOOK",
    "A3": "Editor",
    "A2": "Series Editor",
    "A4": "Translator",
    "AB": "Abstract",
    "AD": "Author Address",
    "AN": "Accession Number",
    "AU": "Author",
    "C3": "Title Prefix",
    "C4": "Reviewer",
    "CA": "Caption",
    "CN": "Call Number",
    "CY": "City",
    "DA": "Date",
    "DB": "Name of Database",
    "DO": "DOI",
    "DP": "Database Provider",
    "ET": "Edition",
    "J2": "Abbreviation",
    "KW": "Keywords",
    "L1": "File Attachments",
    "L4": "Figure",
    "LA": "Language",
    "LB": "Label",
    "M1": "Series Volume",
    "M3": "Type of Work",
    "N1": "Notes",
    "NV": "Number of Volumes",
    "OP": "Original Publication",
    "PB": "Publisher",
    "PY": "Year",
    "RN": "Research Notes",
    "RP": "Reprint Edition",
    "SE": "Pages",
    "SN": "ISBN",
    "SP": "Number of Pages",
    "ST": "Short Title",
    "T2": "Series Title",
    "TA": "Translated Author",
    "TI": "Title",
    "TT": "Translated Title",
    "UR": "URL",
    "VL": "Volume",
    "Y2": "Access Date"
  },
  {
    "TY": "CHAP",
    "A2": "Editor",
    "A3": "Series Editor",
    "A4": "Translator",
    "AB": "Abstract",
    "AD": "Author Address",
    "AN": "Accession Number",
    "AU": "Author",
    "C1": "Section",
    "C3": "Title Prefix",
    "C4": "Reviewer",
    "C5": "Packaging Method",
    "CA": "Caption",
    "CN": "Call Number",
    "CY": "City",
    "DB": "Name of Database",
    "DO": "DOI",
    "DP": "Database Provider",
    "ET": "Edition",
    "J2": "Abbreviation",
    "KW": "Keywords",
    "L1": "File Attachments",
    "L4": "Figure",
    "LA": "Language",
    "LB": "Label",
    "IS": "Number of Volumes",
    "OP": "Original Publication",
    "N1": "Notes",
    "PB": "Publisher",
    "PY": "Year",
    "RI": "Reviewed Item",
    "RN": "Research Notes",
    "RP": "Reprint Edition",
    "SE": "Chapter",
    "SN": "ISBN",
    "SP": "Pages",
    "ST": "Short Title",
    "SV": "Series Volume",
    "T2": "Book Title",
    "T3": "Series Title",
    "TA": "Translated Author",
    "TI": "Title",
    "TT": "Translated Title",
    "UR": "URL",
    "VL": "Volume",
    "Y2": "Access Date"
  },
  {
    "TY": "CASE",
    "A2": "Reporter",
    "A3": "Higher Court",
    "A4": "Counsel",
    "AB": "Abstract",
    "AD": "Author Address",
    "AN": "Accession Number",
    "CA": "Caption",
    "CN": "Call Number",
    "DA": "Date Decided",
    "DB": "Name of Database",
    "DO": "DOI",
    "DP": "Database Provider",
    "ET": "Action of Higher Court",
    "KW": "Keywords",
    "L1": "File Attachments",
    "L4": "Figure",
    "LA": "Language",
    "LB": "Label",
    "M3": "Citation of Reversal",
    "N1": "Notes",
    "NV": "Reporter Abbreviation",
    "OP": "History",
    "PB": "Court",
    "PY": "Year Decided",
    "RN": "Research Notes",
    "SE": "Filed Date",
    "SP": "First Page",
    "ST": "Abbreviated Case Name",
    "T3": "Decision",
    "TA": "Translated Author",
    "TI": "Case Name",
    "TT": "Translated Title",
    "UR": "URL",
    "VL": "Reporter Volume",
    "Y2": "Access Date"
  },
  {
    "TY": "CTLG",
    "A2": "Institution",
    "A4": "Translator",
    "AB": "Abstract",
    "AD": "Author Address",
    "AN": "Accession Number",
    "AU": "Author",
    "C5": "Packaging Method",
    "CA": "Caption",
    "CN": "Call Number",
    "CY": "City",
    "DA": "Date",
    "DB": "Name of Database",
    "DO": "DOI",
    "DP": "Database Provider",
    "ET": "Edition",
    "J2": "Abbreviation",
    "KW": "Keywords",
    "L1": "File Attachments",
    "L4": "Figure",
    "LA": "Language",
    "LB": "Label",
    "M1": "Series Volume",
    "M3": "Type of Work",
    "N1": "Notes",
    "NV": "Catalog Number",
    "OP": "Original Publication",
    "PB": "Publisher",
    "PY": "Year",
    "RN": "Research Notes",
    "RP": "Reprint Edition",
    "SE": "Number of Pages",
    "SN": "ISBN",
    "SP": "Pages",
    "ST": "Short Title",
    "T2": "Series Title",
    "TA": "Translated Author",
    "TI": "Title",
    "TT": "Translated Title",
    "UR": "URL",
    "VL": "Volume",
    "Y2": "Access Date"
  },
  {
    "TY": "CHART",
    "A2": "Name of File",
    "AB": "Abstract",
    "AD": "Author Address",
    "AN": "Accession Number",
    "AU": "Created By",
    "CA": "Caption",
    "CN": "Call Number",
    "CY": "City",
    "DA": "Date",
    "DB": "Name of Database",
    "DO": "DOI",
    "DP": "Database Provider",
    "ET": "Version",
    "KW": "Keywords",
    "L1": "File Attachments",
    "L4": "Figure",
    "LA": "Language",
    "LB": "Label",
    "M1": "Number",
    "M3": "Type of Image",
    "N1": "Notes",
    "PB": "Publisher",
    "PY": "Year",
    "RN": "Research Notes",
    "SP": "Description",
    "T2": "Image Source Program",
    "TA": "Translated Author",
    "TI": "Title",
    "TT": "Translated Title",
    "UR": "URL",
    "VL": "Image Size",
    "Y2": "Access Date"
  },
  {
    "TY": "CLSWK",
    "A2": "Series Editor",
    "A4": "Translator",
    "AB": "Abstract",
    "AD": "Author Address",
    "AN": "Accession Number",
    "AU": "Attribution",
    "CA": "Caption",
    "CN": "Call Number",
    "CY": "City",
    "DB": "Name of Database",
    "DO": "DOI",
    "DP": "Database Provider",
    "ET": "Edition",
    "J2": "Alternate Title",
    "KW": "Keywords",
    "L1": "File Attachments",
    "L4": "Figure",
    "LA": "Language",
    "LB": "Label",
    "M1": "Series Volume",
    "M3": "Type",
    "N1": "Notes",
    "NV": "Number of Volumes",
    "OP": "Original Publication",
    "PB": "Publisher",
    "PY": "Year",
    "RN": "Research Notes",
    "RP": "Reprint Edition",
    "SN": "ISSN/ISBN",
    "SP": "Number of Pages",
    "ST": "Short Title",
    "T2": "Series Title",
    "TA": "Translated Author",
    "TI": "Title",
    "TT": "Translated Title",
    "UR": "URL",
    "VL": "Volume",
    "Y2": "Access Date"
  },
  {
    "TY": "COMP",
    "A2": "Series Editor",
    "AB": "Abstract",
    "AD": "Author Address",
    "AN": "Accession Number",
    "AU": "Programmer",
    "CA": "Caption",
    "CN": "Call Number",
    "CY": "City",
    "DB": "Name of Database",
    "DO": "DOI",
    "DP": "Database Provider",
    "ET": "Version",
    "J2": "Alternate Title",
    "KW": "Keywords",
    "L1": "File Attachments",
    "L4": "Figure",
    "LA": "Language",
    "LB": "Label",
    "M1": "Computer",
    "M3": "Type",
    "N1": "Notes",
    "OP": "Contents",
    "PB": "Publisher",
    "PY": "Year",
    "RN": "Research Notes",
    "SN": "ISBN",
    "SP": "Description",
    "ST": "Short Title",
    "T2": "Series Title",
    "TA": "Translated Author",
    "TI": "Title",
    "TT": "Translated Title",
    "UR": "URL",
    "VL": "Edition",
    "Y2": "Access Date"
  },
  {
    "TY": "CPAPER",
    "A2": "Editor",
    "AB": "Abstract",
    "AD": "Author Address",
    "AN": "Accession Number",
    "AU": "Author",
    "C1": "Place Published",
    "CA": "Caption",
    "CY": "Conference Location",
    "DA": "Date",
    "DB": "Name of Database",
    "DO": "DOI",
    "DP": "Database Provider",
    "KW": "Keywords",
    "L1": "File Attachments",
    "L4": "Figure",
    "LA": "Language",
    "LB": "Label",
    "M3": "Type of Work",
    "N1": "Notes",
    "PB": "Publisher",
    "PY": "Year",
    "RN": "Research Notes",
    "SP": "Pages",
    "T2": "Conference Name",
    "TA": "Translated Author",
    "TI": "Title",
    "TT": "Translated Title",
    "UR": "URL",
    "VL": "Volume",
    "Y2": "Access Date"
  },
  {
    "TY": "CONF",
    "A2": "Editor",
    "A3": "Series Editor",
    "A4": "Sponsor",
    "AB": "Abstract",
    "AD": "Author Address",
    "AN": "Accession Number",
    "AU": "Author",
    "C1": "Place Published",
    "C2": "Year Published",
    "C3": "Proceedings Title",
    "C5": "Packaging Method",
    "CA": "Caption",
    "CN": "Call Number",
    "CY": "Conference Location",
    "DA": "Date",
    "DB": "Name of Database",
    "DO": "DOI",
    "DP": "Database Provider",
    "ET": "Edition",
    "KW": "Keywords",
    "L1": "File Attachments",
    "L4": "Figure",
    "LA": "Language",
    "LB": "Label",
    "M1": "Issue",
    "N1": "Notes",
    "NV": "Number of Volumes",
    "PB": "Publisher",
    "PY": "Year of Conference",
    "RN": "Research Notes",
    "SN": "ISBN",
    "SP": "Pages",
    "ST": "Short Title",
    "T2": "Conference Name",
    "T3": "Series Title",
    "TA": "Translated Author",
    "TI": "Title",
    "TT": "Translated Title",
    "UR": "URL",
    "VL": "Volume",
    "Y2": "Access Date"
  },
  {
    "TY": "DATA",
    "A2": "Producer",
    "A4": "Funding Agency",
    "AB": "Abstract",
    "AD": "Author Address",
    "AN": "Accession Number",
    "AU": "Investigators",
    "C1": "Time Period",
    "C2": "Unit of Observation",
    "C3": "Data Type",
    "C4": "Dataset(s)",
    "CA": "Caption",
    "CN": "Call Number",
    "CY": "City",
    "DA": "Date of Collection",
    "DB": "Name of Database",
    "DO": "DOI",
    "DP": "Database Provider",
    "ET": "Version",
    "J2": "Abbreviation",
    "KW": "Keywords",
    "L1": "File Attachments",
    "L4": "Figure",
    "LA": "Language",
    "LB": "Label",
    "N1": "Notes",
    "NV": "Study Number",
    "OP": "Version History",
    "PB": "Distributor",
    "PY": "Year",
    "RI": "Geographic Coverage",
    "RN": "Research Notes",
    "SE": "Original Release Date",
    "SN": "ISSN",
    "ST": "Short Title",
    "T3": "Series Title",
    "TA": "Translated Author",
    "TI": "Title",
    "TT": "Translated Title",
    "UR": "URL",
    "Y2": "Access Date"
  },
  {
    "TY": "DICT",
    "A2": "Editor",
    "A4": "Translator",
    "AB": "Abstract",
    "AD": "Author Address",
    "AN": "Accession Number",
    "AU": "Author",
    "C1": "Term",
    "CA": "Caption",
    "CN": "Call Number",
    "CY": "City",
    "DB": "Name of Database",
    "DO": "DOI",
    "DP": "Database Provider",
    "ET": "Edition",
    "J2": "Abbreviation",
    "KW": "Keywords",
    "L1": "File Attachments",
    "L4": "Figure",
    "LA": "Language",
    "LB": "Label",
    "M1": "Number",
    "M3": "Type of Work",
    "N1": "Notes",
    "NV": "Number of Volumes",
    "OP": "Original Publication",
    "PB": "Publisher",
    "PY": "Year",
    "RI": "Reviewed Item",
    "RN": "Research Notes",
    "RP": "Reprint Edition",
    "SE": "Version",
    "SN": "ISBN",
    "SP": "Pages",
    "ST": "Short Title",
    "T2": "Dictionary Title",
    "TA": "Translated Author",
    "TI": "Title",
    "TT": "Translated Title",
    "UR": "URL",
    "VL": "Volume",
    "Y2": "Access Date"
  },
  {
    "TY": "EDBOOK",
    "A2": "Series Editor",
    "A4": "Translator",
    "AB": "Abstract",
    "AD": "Editor Address",
    "AN": "Accession Number",
    "AU": "Editor",
    "CA": "Caption",
    "CN": "Call Number",
    "CY": "City",
    "DA": "Date",
    "DB": "Name of Database",
    "DO": "DOI",
    "DP": "Database Provider",
    "ET": "Edition",
    "J2": "Alternate Title",
    "KW": "Keywords",
    "L1": "File Attachments",
    "L4": "Figure",
    "LA": "Language",
    "LB": "Label",
    "M1": "Series Volume",
    "M3": "Type of Work",
    "N1": "Notes",
    "NV": "Number of Volumes",
    "OP": "Original Publication",
    "PB": "Publisher",
    "PY": "Year",
    "RN": "Research Notes",
    "RP": "Reprint Edition",
    "SN": "ISBN",
    "SP": "Number of Pages",
    "ST": "Short Title",
    "T2": "Secondary Title",
    "TA": "Translated Author",
    "TI": "Title",
    "TT": "Translated Title",
    "UR": "URL",
    "VL": "Volume",
    "Y2": "Access Date"
  },
  {
    "TY": "EJOUR",
    "AB": "Abstract",
    "AD": "Author Address",
    "AN": "Accession Number",
    "AU": "Author",
    "C1": "Year Cited",
    "C2": "Date Cited",
    "C3": "PMCID",
    "C4": "Reviewer",
    "C5": "Issue Title",
    "C6": "NIHMSID",
    "C7": "Article Number",
    "CA": "Caption",
    "CY": "Place Published",
    "DA": "Date Accessed",
    "DB": "Name of Database",
    "DO": "DOI",
    "DP": "Database Provider",
    "ET": "Edition",
    "J2": "Alternate Title",
    "KW": "Keywords",
    "L1": "File Attachments",
    "L4": "Figure",
    "LA": "Language",
    "LB": "Label",
    "M1": "Issue",
    "M3": "Type of Work",
    "N1": "Notes",
    "NV": "Document Number",
    "PB": "Publisher",
    "PY": "Year",
    "RI": "Reviewed Item",
    "RN": "Research Notes",
    "RP": "Reprint Edition",
    "SE": "E-Pub Date",
    "SN": "ISSN",
    "SP": "Pages",
    "ST": "Short Title",
    "T2": "Periodical Title",
    "T3": "Website Title",
    "TA": "Translated Author",
    "TI": "Title",
    "TT": "Translated Title",
    "UR": "URL",
    "VL": "Volume"
  },
  {
    "TY": "EBOOK",
    "A2": "Editor",
    "A3": "Series Editor",
    "AB": "Abstract",
    "AD": "Author Address",
    "AN": "Accession Number",
    "AU": "Author",
    "C1": "Year Cited",
    "C2": "Date Cited",
    "C3": "Title Prefix",
    "C4": "Reviewer",
    "C5": "Last Update Date",
    "C6": "NIHMSID",
    "C7": "PMCID",
    "CA": "Caption",
    "CN": "Call Number",
    "CY": "Place Published",
    "DA": "Date Accessed",
    "DB": "Name of Database",
    "DO": "DOI",
    "DP": "Database Provider",
    "ET": "Edition",
    "KW": "Keywords",
    "L1": "File Attachments",
    "L4": "Figure",
    "LA": "Language",
    "LB": "Label",
    "M3": "Type of Medium",
    "N1": "Notes",
    "NV": "Version",
    "OP": "Original Publication",
    "PB": "Publisher",
    "PY": "Year",
    "RI": "Reviewed Item",
    "RN": "Research Notes",
    "RP": "Reprint Edition",
    "SN": "ISBN",
    "SP": "Number of Pages",
    "T2": "Secondary Title",
    "T3": "Series Title",
    "TA": "Translated Author",
    "TI": "Title",
    "TT": "Translated Title",
    "UR": "URL",
    "VL": "Volume"
  },
  {
    "TY": "ECHAP",
    "A2": "Editor",
    "AB": "Abstract",
    "AD": "Author Address",
    "AN": "Accession Number",
    "AU": "Author",
    "C1": "Section",
    "C3": "Title Prefix",
    "C4": "Reviewer",
    "C5": "Packaging Method",
    "C6": "NIHMSID",
    "C7": "PMCID",
    "CA": "Caption",
    "CN": "Call Number",
    "CY": "Place Published",
    "DA": "Date Accessed",
    "DB": "Name of Database",
    "DO": "DOI",
    "DP": "Database Provider",
    "ET": "Edition",
    "KW": "Keywords",
    "L1": "File Attachments",
    "L4": "Figure",
    "LA": "Language",
    "LB": "Label",
    "M1": "Chapter",
    "M3": "Type of Work",
    "N1": "Notes",
    "NV": "Number of Volumes",
    "OP": "Original Publication",
    "PB": "Publisher",
    "PY": "Year",
    "RI": "Reviewed Item",
    "RN": "Research Notes",
    "RP": "Reprint Edition",
    "SN": "ISBN",
    "SP": "Pages",
    "ST": "Short Title",
    "T2": "Book Title",
    "T3": "Series Title",
    "TA": "Translated Author",
    "TI": "Title",
    "TT": "Translated Title",
    "UR": "URL",
    "VL": "Volume",
    "Y2": "Access Date"
  },
  {
    "TY": "ENCYC",
    "A2": "Editor",
    "A4": "Translator",
    "AB": "Abstract",
    "AD": "Author Address",
    "AN": "Accession Number",
    "AU": "Author",
    "C1": "Term",
    "CA": "Caption",
    "CN": "Call Number",
    "CY": "City",
    "DA": "Date",
    "DB": "Name of Database",
    "DO": "DOI",
    "DP": "Database Provider",
    "ET": "Edition",
    "J2": "Abbreviation",
    "KW": "Keywords",
    "L1": "File Attachments",
    "L4": "Figure",
    "LA": "Language",
    "LB": "Label",
    "N1": "Notes",
    "NV": "Number of Volumes",
    "OP": "Original Publication",
    "PB": "Publisher",
    "PY": "Year",
    "RI": "Reviewed Item",
    "RN": "Research Notes",
    "RP": "Reprint Edition",
    "SN": "ISBN",
    "SP": "Pages",
    "ST": "Short Title",
    "T2": "Encyclopedia Title",
    "TA": "Translated Author",
    "TI": "Title",
    "TT": "Translated Title",
    "UR": "URL",
    "VL": "Volume",
    "Y2": "Access Date"
  },
  {
    "TY": "EQUA",
    "A2": "Name of File",
    "AB": "Abstract",
    "AD": "Author Address",
    "AN": "Accession Number",
    "AU": "Created By",
    "CA": "Caption",
    "CN": "Call Number",
    "CY": "City",
    "DA": "Date",
    "DB": "Name of Database",
    "DO": "DOI",
    "DP": "Database Provider",
    "ET": "Version",
    "KW": "Keywords",
    "L1": "File Attachments",
    "L4": "Figure",
    "LA": "Language",
    "LB": "Label",
    "M1": "Number",
    "M3": "Type of Image",
    "N1": "Notes",
    "PB": "Publisher",
    "PY": "Year",
    "RN": "Research Notes",
    "SP": "Description",
    "T2": "Image Source Program",
    "TA": "Translated Author",
    "TI": "Title",
    "TT": "Translated Title",
    "UR": "URL",
    "VL": "Image Size",
    "Y2": "Access Date"
  },
  {
    "TY": "FIGURE",
    "A2": "Name of File",
    "AB": "Abstract",
    "AD": "Author Address",
    "AN": "Accession Number",
    "AU": "Created By",
    "CN": "Call Number",
    "CT": "Caption",
    "CY": "City",
    "DA": "Date",
    "DB": "Name of Database",
    "DO": "DOI",
    "DP": "Database Provider",
    "ET": "Version",
    "KW": "Keywords",
    "L1": "File Attachments",
    "L4": "Figure",
    "LA": "Language",
    "LB": "Label",
    "M1": "Number",
    "M3": "Type of Image",
    "N1": "Notes",
    "PB": "Publisher",
    "PY": "Year",
    "RN": "Research Notes",
    "SP": "Description",
    "T2": "Image Source Program",
    "TA": "Translated Author",
    "TI": "Title",
    "TT": "Translated Title",
    "UR": "URL",
    "VL": "Image Size",
    "Y2": "Access Date"
  },
  {
    "TY": "MPCT",
    "A2": "Series Director",
    "A3": "Producer",
    "A4": "Performers",
    "AB": "Synopsis",
    "AD": "Author Address",
    "AN": "Accession Number",
    "AU": "Director",
    "C1": "Cast",
    "C2": "Credits",
    "C4": "Genre",
    "C5": "Format",
    "CA": "Caption",
    "CN": "Call Number",
    "CY": "Country",
    "DA": "Date Released",
    "DB": "Name of Database",
    "DO": "DOI",
    "DP": "Database Provider",
    "ET": "Edition",
    "J2": "Alternate Title",
    "KW": "Keywords",
    "L1": "File Attachments",
    "L4": "Figure",
    "LA": "Language",
    "LB": "Label",
    "M3": "Medium",
    "N1": "Notes",
    "PB": "Distributor",
    "PY": "Year Released",
    "RN": "Research Notes",
    "SP": "Running Time",
    "ST": "Short Title",
    "T2": "Series Title",
    "TA": "Translated Author",
    "TI": "Title",
    "TT": "Translated Title",
    "UR": "URL",
    "Y2": "Access Date"
  },
  {
    "TY": "GOVDOC",
    "A2": "Department",
    "AB": "Abstract",
    "AD": "Author Address",
    "AN": "Accession Number",
    "AU": "Author",
    "C1": "Government Body",
    "C2": "Congress Number",
    "C3": "Congress Session",
    "CA": "Caption",
    "CY": "City",
    "DB": "Name of Database",
    "DO": "DOI",
    "DP": "Database Provider",
    "ET": "Edition",
    "KW": "Keywords",
    "L1": "File Attachments",
    "L4": "Figure",
    "LA": "Language",
    "LB": "Label",
    "M1": "Issue",
    "N1": "Notes",
    "PB": "Publisher",
    "PY": "Year",
    "RN": "Research Notes",
    "SE": "Section",
    "SN": "Report Number",
    "SP": "Pages",
    "T3": "Series Title",
    "TA": "Translated Author",
    "TI": "Title",
    "TT": "Translated Title",
    "UR": "URL",
    "VL": "Volume",
    "Y2": "Access Date"
  },
  {
    "TY": "GRANT",
    "A4": "Translator",
    "AB": "Abstract",
    "AD": "Author Address",
    "AN": "Accession Number",
    "AU": "Investigators",
    "C1": "Contact Name",
    "C2": "Contact Address",
    "C3": "Contact Phone",
    "C4": "Contact Fax",
    "C5": "Funding Number",
    "C6": "CFDA Number",
    "CA": "Caption",
    "CN": "Call Number",
    "CY": "Activity Location",
    "DA": "Deadline",
    "DB": "Name of Database",
    "DO": "DOI",
    "DP": "Database Provider",
    "ET": "Requirement",
    "J2": "Abbreviation",
    "KW": "Keywords",
    "L1": "File Attachments",
    "L4": "Figure",
    "LA": "Language",
    "LB": "Label",
    "M1": "Status",
    "M3": "Funding Type",
    "N1": "Notes",
    "NV": "Amount Received",
    "OP": "Original Grant Number",
    "PB": "Sponsoring Agency",
    "PY": "Year",
    "RI": "Reviewed Item",
    "RN": "Research Notes",
    "RP": "Review Date",
    "SE": "Duration of Grant",
    "SP": "Pages",
    "ST": "Short Title",
    "TA": "Translated Author",
    "TI": "Title of Grant",
    "TT": "Translated Title",
    "UR": "URL",
    "VL": "Amount Requested",
    "Y2": "Access Date"
  },
  {
    "TY": "HEAR",
    "AB": "Abstract",
    "AD": "Author Address",
    "AN": "Accession Number",
    "CA": "Caption",
    "CN": "Call Number",
    "CY": "City",
    "C2": "Congress Number",
    "DA": "Date",
    "DB": "Name of Database",
    "DO": "DOI",
    "DP": "Database Provider",
    "ET": "Session",
    "KW": "Keywords",
    "L1": "File Attachments",
    "L4": "URL",
    "LA": "Language",
    "LB": "Label",
    "M1": "Document Number",
    "N1": "Notes",
    "NV": "Number of Volumes",
    "OP": "History",
    "PB": "Publisher",
    "PY": "Year",
    "RN": "Research Notes",
    "SN": "ISBN",
    "SP": "Pages",
    "ST": "Short Title",
    "T2": "Committee",
    "T3": "Legislative Body",
    "TA": "Translated Author",
    "TI": "Title",
    "TT": "Translated Title",
    "UR": "URL",
    "Y2": "Access Date"
  },
  {
    "TY": "LEGAL",
    "A2": "Issuing Organization",
    "AB": "Abstract",
    "AD": "Author Address",
    "AN": "Accession Number",
    "AU": "Author",
    "CA": "Caption",
    "CN": "Call Number",
    "CY": "Place Published",
    "DA": "Date of Code Edition",
    "DB": "Name of Database",
    "DO": "DOI",
    "DP": "Database Provider",
    "ET": "Edition",
    "J2": "Abbreviation",
    "KW": "Keywords",
    "L1": "File Attachments",
    "L4": "Figure",
    "LA": "Language",
    "LB": "Label",
    "M1": "Start Page",
    "M3": "Type of Work",
    "N1": "Notes",
    "NV": "Session Number",
    "OP": "History",
    "PB": "Publisher",
    "PY": "Year",
    "RN": "Research Notes",
    "SE": "Section Number",
    "SN": "Document Number",
    "SP": "Pages",
    "T2": "Title Number",
    "T3": "Supplement No.",
    "TA": "Translated Author",
    "TI": "Title",
    "TT": "Translated Title",
    "UR": "URL",
    "VL": "Rule Number",
    "Y2": "Access Date"
  },
  {
    "TY": "MGZN",
    "AB": "Abstract",
    "AD": "Author Address",
    "AN": "Accession Number",
    "AU": "Author",
    "CA": "Caption",
    "CN": "Call Number",
    "CY": "Place Published",
    "DA": "Date",
    "DB": "Name of Database",
    "DO": "DOI",
    "DP": "Database Provider",
    "ET": "Edition",
    "J2": "Alternate Magazine",
    "KW": "Keywords",
    "L1": "File Attachments",
    "L4": "Figure",
    "LA": "Language",
    "LB": "Label",
    "M1": "Issue Number",
    "M3": "Type of Article",
    "N1": "Notes",
    "NV": "Frequency",
    "OP": "Original Publication",
    "PB": "Publisher",
    "PY": "Year",
    "RI": "Reviewed Item",
    "RN": "Research Notes",
    "RP": "Reprint Edition",
    "SE": "Start Page",
    "SN": "ISSN",
    "SP": "Pages",
    "ST": "Short Title",
    "T2": "Magazine",
    "TA": "Translated Author",
    "TI": "Title",
    "TT": "Translated Title",
    "UR": "URL",
    "VL": "Volume",
    "Y2": "Access Date"
  },
  {
    "TY": "MANSCPT",
    "AB": "Abstract",
    "AD": "Author Address",
    "AN": "Accession Number",
    "AU": "Author",
    "CN": "Call Number",
    "CA": "Caption",
    "CY": "City",
    "DA": "Date",
    "DB": "Name of Database",
    "DO": "DOI",
    "DP": "Database Provider",
    "ET": "Description of Material",
    "J2": "Abbreviation",
    "KW": "Keywords",
    "L1": "File Attachments",
    "L4": "Figure",
    "LA": "Language",
    "LB": "Label",
    "M1": "Folio Number",
    "M3": "Type of Work",
    "N1": "Notes",
    "NV": "Manuscript Number",
    "PB": "Library/Archive",
    "PY": "Year",
    "RP": "Reprint Edition",
    "RN": "Research Notes",
    "SE": "Start Page",
    "SP": "Pages",
    "ST": "Short Title",
    "T2": "Collection Title",
    "TA": "Translated Author",
    "TI": "Title",
    "TT": "Translated Title",
    "UR": "URL",
    "VL": "Volume/Storage Container",
    "Y2": "Access Date"
  },
  {
    "TY": "MAP",
    "A2": "Series Editor",
    "AB": "Abstract",
    "AD": "Author Address",
    "AN": "Accession Number",
    "AU": "Cartographer",
    "C1": "Scale",
    "C2": "Area",
    "C3": "Size",
    "C5": "Packaging Method",
    "CA": "Caption",
    "CN": "Call Number",
    "CY": "City",
    "DA": "Date",
    "DB": "Name of Database",
    "DO": "DOI",
    "DP": "Database Provider",
    "ET": "Edition",
    "J2": "Alternate Title",
    "KW": "Keywords",
    "L1": "File Attachments",
    "L4": "Figure",
    "LA": "Language",
    "LB": "Label",
    "M3": "Type",
    "N1": "Notes",
    "PB": "Publisher",
    "PY": "Year",
    "RN": "Research Notes",
    "RP": "Reprint Edition",
    "SN": "ISBN",
    "SP": "Description",
    "ST": "Short Title",
    "T2": "Series Title",
    "TA": "Translated Author",
    "TI": "Title",
    "TT": "Translated Title",
    "UR": "URL",
    "Y2": "Access Date"
  },
  {
    "TY": "MUSIC",
    "A2": "Editor",
    "A3": "Series Editor",
    "A4": "Producer",
    "AB": "Abstract",
    "AD": "Author Address",
    "AN": "Accession Number",
    "AU": "Composer",
    "C1": "Format of Music",
    "C2": "Form of Composition",
    "C3": "Music Parts",
    "C4": "Target Audience",
    "C5": "Accompanying Matter",
    "CA": "Caption",
    "CN": "Call Number",
    "CY": "Place Published",
    "DA": "Date",
    "DB": "Name of Database",
    "DO": "DOI",
    "DP": "Database Provider",
    "ET": "Edition",
    "KW": "Keywords",
    "L1": "File Attachments",
    "L4": "Figure",
    "LA": "Language",
    "LB": "Label",
    "M3": "Form of Item",
    "N1": "Notes",
    "NV": "Number of Volumes",
    "OP": "Original Publication",
    "PB": "Publisher",
    "PY": "Year",
    "RN": "Research Notes",
    "RP": "Reprint Edition",
    "SE": "Section",
    "SN": "ISSN",
    "SP": "Pages",
    "ST": "Short Title",
    "T2": "Album Title",
    "T3": "Series Title",
    "TA": "Translated Author",
    "TI": "Title",
    "TT": "Translated Title",
    "UR": "URL",
    "VL": "Volume",
    "Y2": "Access Date"
  },
  {
    "TY": "NEWS",
    "AB": "Abstract",
    "AD": "Author Address",
    "AN": "Accession Number",
    "AU": "Reporter",
    "C1": "Column",
    "C2": "Issue",
    "CA": "Caption",
    "CN": "Call Number",
    "CY": "City",
    "DB": "Name of Database",
    "DP": "Database Provider",
    "ET": "Edition",
    "DO": "DOI",
    "SP": "Pages",
    "KW": "Keywords",
    "LA": "Language",
    "L1": "Figure",
    "L4": "File Attachments",
    "M1": "Start Page",
    "M3": "Type of Article",
    "SE": "Section",
    "N1": "Notes",
    "NV": "Frequency",
    "PB": "Publisher",
    "PY": "Year",
    "RI": "Reviewed Item",
    "RN": "Research Notes",
    "RP": "Reprint Edition",
    "SN": "ISSN",
    "ST": "Short Title",
    "T2": "Newspaper",
    "TI": "Title",
    "TT": "Translated Title",
    "TA": "Translated Author",
    "UR": "URL",
    "VL": "Volume",
    "Y2": "Access Date"
  },
  {
    "TY": "DBASE",
    "AB": "Abstract",
    "AD": "Author Address",
    "AN": "Accession Number",
    "AU": "Author",
    "CA": "Caption",
    "CY": "Place Published",
    "DA": "Date Accessed",
    "DB": "Name of Database",
    "DO": "DOI",
    "DP": "Database Provider",
    "ET": "Date Published",
    "KW": "Keywords",
    "L1": "File Attachments",
    "L4": "Figure",
    "LA": "Language",
    "LB": "Label",
    "M3": "Type of Work",
    "N1": "Notes",
    "PB": "Publisher",
    "PY": "Year",
    "RN": "Research Notes",
    "SN": "Report Number",
    "SP": "Pages",
    "T2": "Periodical",
    "TA": "Translated Author",
    "TI": "Title",
    "TT": "Translated Title",
    "UR": "URL",
    "VL": "Volume"
  },
  {
    "TY": "MULTI",
    "A2": "Series Editor",
    "AB": "Abstract",
    "AD": "Author Address",
    "AN": "Accession Number",
    "AU": "Created By",
    "C1": "Year Cited",
    "C2": "Date Cited",
    "C5": "Format/Length",
    "CA": "Caption",
    "DA": "Date Accessed",
    "DB": "Name of Database",
    "DO": "DOI",
    "DP": "Database Provider",
    "KW": "Keywords",
    "L1": "File Attachments",
    "L4": "Figure",
    "LA": "Language",
    "LB": "Label",
    "M1": "Number of Screens",
    "M3": "Type of Work",
    "N1": "Notes",
    "PB": "Distributor",
    "PY": "Year",
    "RN": "Research Notes",
    "T2": "Series Title",
    "TA": "Translated Author",
    "TI": "Title",
    "TT": "Translated Title",
    "UR": "URL"
  },
  {
    "TY": "PAMP",
    "A2": "Institution",
    "A4": "Translator",
    "AB": "Abstract",
    "AD": "Author Address",
    "AN": "Accession Number",
    "AU": "Author",
    "C5": "Packaging Method",
    "CA": "Caption",
    "CN": "Call Number",
    "CY": "City",
    "DA": "Date",
    "DB": "Name of Database",
    "DO": "DOI",
    "DP": "Database Provider",
    "ET": "Edition",
    "J2": "Abbreviation",
    "KW": "Keywords",
    "L1": "File Attachments",
    "L4": "Figure",
    "LA": "Language",
    "LB": "Label",
    "M1": "Series Volume",
    "M3": "Type of Work",
    "N1": "Notes",
    "OP": "Original Publication",
    "PB": "Publisher",
    "PY": "Year",
    "RN": "Research Notes",
    "RP": "Reprint Edition",
    "M2": "Number of Pages",
    "SN": "ISBN",
    "SP": "Pages",
    "ST": "Short Title",
    "T2": "Published Source",
    "TA": "Translated Author",
    "TI": "Title",
    "TT": "Translated Title",
    "UR": "URL",
    "VL": "Number",
    "Y2": "Access Date"
  },
  {
    "TY": "PAT",
    "A2": "Issuing Organization",
    "A3": "International Author",
    "AB": "Abstract",
    "AD": "Inventor Address",
    "AN": "Accession Number",
    "AU": "Inventor",
    "C2": "Issue Date",
    "C3": "Designated States",
    "C4": "Attorney/Agent",
    "C5": "References",
    "C6": "Legal Status",
    "CA": "Caption",
    "CN": "Call Number",
    "CY": "Country",
    "DA": "Date",
    "DB": "Name of Database",
    "DO": "DOI",
    "DP": "Database Provider",
    "ET": "International Patent Classification",
    "KW": "Keywords",
    "L1": "File Attachments",
    "L4": "Figure",
    "LA": "Language",
    "LB": "Label",
    "M1": "Application Number",
    "M3": "Patent Type",
    "N1": "Notes",
    "NV": "US Patent Classification",
    "OP": "Priority Numbers",
    "PB": "Assignee",
    "PY": "Year",
    "RN": "Research Notes",
    "RP": "Notes",
    "SE": "International Patent Number",
    "SN": "Patent Number",
    "SP": "Pages",
    "ST": "Short Title",
    "T2": "Published Source",
    "T3": "International Title",
    "TA": "Translated Author",
    "TI": "Title",
    "TT": "Translated Title",
    "UR": "URL",
    "VL": "Patent Version Number",
    "Y2": "Access Date"
  },
  {
    "TY": "PCOMM",
    "A2": "Recipient",
    "AB": "Abstract",
    "AD": "Author Address",
    "AN": "Accession Number",
    "AU": "Author",
    "C1": "Sender's E-Mail",
    "C2": "Recipients E-Mail",
    "CN": "Call Number",
    "CA": "Caption",
    "CY": "City",
    "DA": "Date",
    "DB": "Name of Database",
    "DO": "DOI",
    "DP": "Database Provider",
    "ET": "Description",
    "J2": "Abbreviation",
    "KW": "Keywords",
    "L1": "File Attachments",
    "L4": "Figure",
    "LA": "Language",
    "LB": "Label",
    "M1": "Folio Number",
    "M3": "Type",
    "N1": "Notes",
    "NV": "Communication Number",
    "PB": "Publisher",
    "PY": "Year",
    "RN": "Research Notes",
    "SP": "Pages",
    "ST": "Short Title",
    "TA": "Translated Author",
    "TI": "Title",
    "TT": "Translated Title",
    "UR": "URL",
    "Y2": "Access Date"
  },
  {
    "TY": "ICOMM",
    "A2": "Recipient",
    "AB": "Abstract",
    "AD": "Author Address",
    "AN": "Accession Number",
    "AU": "Author",
    "C1": "Sender's E-Mail",
    "C2": "Recipients E-Mail",
    "CN": "Call Number",
    "CA": "Caption",
    "CY": "City",
    "DA": "Date",
    "DB": "Name of Database",
    "DO": "DOI",
    "DP": "Database Provider",
    "ET": "Description",
    "J2": "Abbreviation",
    "KW": "Keywords",
    "L1": "File Attachments",
    "L4": "Figure",
    "LA": "Language",
    "LB": "Label",
    "M1": "Folio Number",
    "M3": "Type",
    "N1": "Notes",
    "NV": "Communication Number",
    "PB": "Publisher",
    "PY": "Year",
    "RN": "Research Notes",
    "SP": "Pages",
    "ST": "Short Title",
    "TA": "Translated Author",
    "TI": "Title",
    "TT": "Translated Title",
    "UR": "URL",
    "Y2": "Access Date"
  },
  {
    "TY": "RPRT",
    "A2": "Series Editor",
    "A3": "Publisher",
    "A4": "Department/Division",
    "AB": "Abstract",
    "AD": "Author Address",
    "AN": "Accession Number",
    "AU": "Author",
    "CA": "Caption",
    "CN": "Call Number",
    "CY": "City",
    "C6": "Issue",
    "DA": "Date",
    "DB": "Name of Database",
    "DO": "DOI",
    "DP": "Database Provider",
    "ET": "Edition",
    "J2": "Alternate Title",
    "KW": "Keywords",
    "L1": "File Attachments",
    "L4": "Figure",
    "LA": "Language",
    "LB": "Label",
    "M1": "Document Number",
    "M3": "Type",
    "N1": "Notes",
    "NV": "Series Volume",
    "OP": "Contents",
    "PB": "Institution",
    "PY": "Year",
    "RN": "Research Notes",
    "RP": "Notes",
    "SN": "Report Number",
    "SP": "Pages",
    "ST": "Short Title",
    "T2": "Series Title",
    "TA": "Translated Author",
    "TI": "Title",
    "TT": "Translated Title",
    "UR": "URL",
    "VL": "Volume",
    "Y2": "Access Date"
  },
  {
    "TY": "SER",
    "A2": "Editor",
    "A3": "Series Editor",
    "A4": "Volume Editor",
    "AB": "Abstract",
    "AD": "Author Address",
    "AN": "Accession Number",
    "AU": "Author",
    "C1": "Section",
    "C2": "Report Number",
    "C5": "Packaging Method",
    "CA": "Caption",
    "CN": "Call Number",
    "CY": "City",
    "DA": "Date",
    "DB": "Name of Database",
    "DO": "DOI",
    "DP": "Database Provider",
    "ET": "Edition",
    "J2": "Abbreviation",
    "KW": "Keywords",
    "L1": "File Attachments",
    "L4": "Figure",
    "LA": "Language",
    "LB": "Label",
    "M1": "Series Volume",
    "M3": "Type of Work",
    "N1": "Notes",
    "NV": "Number of Volumes",
    "OP": "Original Publication",
    "PB": "Publisher",
    "PY": "Year",
    "RI": "Reviewed Item",
    "RN": "Research Notes",
    "RP": "Reprint Edition",
    "SE": "Chapter",
    "SN": "ISBN",
    "SP": "Pages",
    "ST": "Short Title",
    "T2": "Secondary Title",
    "T3": "Series Title",
    "TA": "Translated Author",
    "TI": "Title",
    "TT": "Translated Title",
    "UR": "URL",
    "VL": "Volume",
    "Y2": "Access Date"
  },
  {
    "TY": "STAND",
    "AB": "Abstract",
    "AD": "Author Address",
    "AN": "Accession Number",
    "AU": "Institution",
    "CA": "Caption",
    "CN": "Call Number",
    "CY": "Place Published",
    "DA": "Date",
    "DB": "Name of Database",
    "DO": "DOI",
    "DP": "Database Provider",
    "J2": "Abbreviation",
    "KW": "Keywords",
    "L1": "File Attachments",
    "L4": "Figure",
    "LA": "Language",
    "LB": "Label",
    "M1": "Start Page",
    "M3": "Type of Work",
    "N1": "Notes",
    "NV": "Session Number",
    "PB": "Publisher",
    "PY": "Year",
    "RN": "Research Notes",
    "SE": "Section Number",
    "SN": "Document Number",
    "SP": "Pages",
    "T2": "Section Title",
    "T3": "Paper Number",
    "TA": "Translated Author",
    "TI": "Title",
    "TT": "Translated Title",
    "UR": "URL",
    "VL": "Rule Number",
    "Y2": "Access Date"
  },
  {
    "TY": "STAT",
    "AB": "Abstract",
    "AD": "Author Address",
    "AN": "Accession Number",
    "CA": "Caption",
    "C5": "Publisher",
    "C6": "Volume",
    "CN": "Call Number",
    "CY": "Country",
    "DA": "Date Enacted",
    "DB": "Name of Database",
    "DO": "DOI",
    "DP": "Database Provider",
    "ET": "Session",
    "J2": "Abbreviation",
    "KW": "Keywords",
    "L1": "File Attachments",
    "L4": "Figure",
    "LA": "Language",
    "LB": "Label",
    "M1": "Public Law Number",
    "N1": "Notes",
    "NV": "Statute Number",
    "OP": "History",
    "PB": "Source",
    "PY": "Year",
    "RI": "Article Number",
    "RN": "Research Notes",
    "SE": "Section",
    "SP": "Pages",
    "ST": "Short Title",
    "T2": "Code",
    "T3": "International Source",
    "TA": "Translated Author",
    "TI": "Name of Act",
    "TT": "Translated Title",
    "UR": "URL",
    "VL": "Code Number",
    "Y2": "Date Enacted"
  },
  {
    "TY": "THES",
    "A3": "Advisor",
    "AB": "Abstract",
    "AD": "Author Address",
    "AN": "Accession Number",
    "AU": "Author",
    "CA": "Caption",
    "CN": "Call Number",
    "CY": "City",
    "DA": "Date",
    "DB": "Name of Database",
    "DO": "DOI",
    "DP": "Database Provider",
    "KW": "Keywords",
    "L1": "File Attachments",
    "L4": "Figure",
    "LA": "Language",
    "LB": "Label",
    "M1": "Document Number",
    "M3": "Thesis Type",
    "N1": "Notes",
    "PB": "University",
    "PY": "Year",
    "RN": "Research Notes",
    "SP": "Number of Pages",
    "ST": "Short Title",
    "T2": "Academic Department",
    "TA": "Translated Author",
    "TI": "Title",
    "TT": "Translated Title",
    "UR": "URL",
    "VL": "Degree",
    "Y2": "Access Date"
  },
  {
    "TY": "UNPB",
    "A2": "Series Editor",
    "AB": "Abstract",
    "AD": "Author Address",
    "AU": "Author",
    "CA": "Caption",
    "CY": "City",
    "DA": "Date",
    "DB": "Name of Database",
    "DO": "DOI",
    "DP": "Database Provider",
    "J2": "Abbreviation",
    "KW": "Keywords",
    "L1": "File Attachments",
    "L4": "Figure",
    "LA": "Language",
    "LB": "Label",
    "M1": "Number",
    "M3": "Type of Work",
    "N1": "Notes",
    "PB": "Institution",
    "PY": "Year",
    "RN": "Research Notes",
    "SP": "Pages",
    "ST": "Short Title",
    "T2": "Series Title",
    "T3": "Department",
    "TA": "Translated Author",
    "TI": "Title of Work",
    "TT": "Translated Title",
    "UR": "URL",
    "Y2": "Access Date"
  },
  {
    "TY": "ELEC",
    "A2": "Series Editor",
    "AB": "Abstract",
    "AD": "Author Address",
    "AN": "Accession Number",
    "AU": "Author",
    "C1": "Year Cited",
    "C2": "Date Cited",
    "CA": "Caption",
    "CN": "Call Number",
    "CY": "City",
    "DA": "Last Update Date",
    "DB": "Name of Database",
    "DO": "DOI",
    "DP": "Database Provider",
    "ET": "Edition",
    "J2": "Alternate Title",
    "KW": "Keywords",
    "L1": "File Attachments",
    "L4": "Figure",
    "LA": "Language",
    "LB": "Label",
    "M1": "Access Date",
    "M3": "Type of Medium",
    "N1": "Notes",
    "OP": "Contents",
    "PB": "Publisher",
    "PY": "Year",
    "RN": "Research Notes",
    "SN": "ISBN",
    "SP": "Description",
    "ST": "Short Title",
    "T2": "Series Title",
    "TA": "Translated Author",
    "TI": "Title",
    "TT": "Translated Title",
    "UR": "URL",
    "VL": "Access Year"
  }
]